<?xml version="1.0" encoding="UTF-8" standalone="yes"?>
<w:ftr xmlns:wpc="http://schemas.microsoft.com/office/word/2010/wordprocessingCanvas" xmlns:cx="http://schemas.microsoft.com/office/drawing/2014/chartex" xmlns:mc="http://schemas.openxmlformats.org/markup-compatibility/2006" xmlns:o="urn:schemas-microsoft-com:office:office" xmlns:r="http://schemas.openxmlformats.org/officeDocument/2006/relationships" xmlns:m="http://schemas.openxmlformats.org/officeDocument/2006/math" xmlns:v="urn:schemas-microsoft-com:vml" xmlns:wp14="http://schemas.microsoft.com/office/word/2010/wordprocessingDrawing" xmlns:wp="http://schemas.openxmlformats.org/drawingml/2006/wordprocessingDrawing" xmlns:w10="urn:schemas-microsoft-com:office:word" xmlns:w="http://schemas.openxmlformats.org/wordprocessingml/2006/main" xmlns:w14="http://schemas.microsoft.com/office/word/2010/wordml" xmlns:w15="http://schemas.microsoft.com/office/word/2012/wordml" xmlns:w16se="http://schemas.microsoft.com/office/word/2015/wordml/symex" xmlns:wpg="http://schemas.microsoft.com/office/word/2010/wordprocessingGroup" xmlns:wpi="http://schemas.microsoft.com/office/word/2010/wordprocessingInk" xmlns:wne="http://schemas.microsoft.com/office/word/2006/wordml" xmlns:wps="http://schemas.microsoft.com/office/word/2010/wordprocessingShape" mc:Ignorable="w14 w15 w16se wp14"><w:p w:rsidR="005A2DAD" w:rsidRPr="00AB0075" w:rsidRDefault="005A2DAD" w:rsidP="0050452F"><w:pPr><w:pStyle w:val="llb"/><w:pBdr><w:top w:val="single" w:sz="12" w:space="4" w:color="auto"/></w:pBdr><w:tabs><w:tab w:val="clear" w:pos="4536"/><w:tab w:val="clear" w:pos="9072"/><w:tab w:val="center" w:pos="4680"/><w:tab w:val="right" w:pos="9540"/></w:tabs><w:spacing w:before="60" w:after="60"/><w:rPr><w:rFonts w:ascii="Arial" w:hAnsi="Arial" w:cs="Arial"/><w:sz w:val="18"/><w:szCs w:val="18"/></w:rPr></w:pPr><w:r><w:rPr><w:rFonts w:ascii="Arial" w:hAnsi="Arial" w:cs="Arial"/><w:sz w:val="18"/><w:szCs w:val="18"/></w:rPr><w:t>Verziószám: 10</w:t></w:r><w:r w:rsidRPr="001A4488"><w:rPr><w:rFonts w:ascii="Arial" w:hAnsi="Arial" w:cs="Arial"/><w:sz w:val="18"/><w:szCs w:val="18"/></w:rPr><w:tab/></w:r><w:r><w:rPr><w:rFonts w:ascii="Arial" w:hAnsi="Arial" w:cs="Arial"/><w:sz w:val="16"/><w:szCs w:val="16"/></w:rPr><w:t>Szerkesztés lezárva: 2021.01.01.</w:t></w:r></w:p></w:ftr>